{
    "version": "https://jsonfeed.org/version/1",
    "title": "新浪新闻",
    "home_page_url": "https://pluckhuang.github.io/realtime-news/",
    "feed_url": "https://pluckhuang.github.io/realtime-news/rss.json",
    "description": "新浪全球实时财经新闻直播",
    "items": [
        {
            "id": 2080322,
            "content_html": "",
            "title": "【施耐德CEO赵国华：电气化是唯一一个可以使能源脱碳的方式】施耐德电气公司董事会主席、首席执行官赵国华先生在中国发展高层论坛上表示：电气化可以说是唯一一个可以使能源脱碳的方式，汽车的电气化当然也是我们现在最为期待的一种方式；包括夏季的供凉以及冬季的供暖，空气的调节、温度的调节；在整个工业当中，我们也是看到了电气化的趋势；如果我们想要实现这一点，我们是需要合作的。",
            "date_modified": "2021-03-20T13:11:29.000Z"
        },
        {
            "id": 2080321,
            "content_html": "",
            "url": "https://finance.sina.cn/7x24/2021-03-20/detail-ikkntiam5859092.d.html",
            "title": "【王一鸣：未来五年年均经济增速约在5%-5.5%区间】中国国际经济交流中心副理事长王一鸣3月20日在中国发展高层论坛2021年会上表示，未来五年大体的年均经济增长速度将处在5%至5.5%的区间；由于外部环境的不确定性，给出精确值很困难。（中证报）",
            "date_modified": "2021-03-20T13:10:26.000Z"
        },
        {
            "id": 2080320,
            "content_html": "",
            "title": "【中国银行刘金：我国商业银行的信用风险在可控范围内】刘金认为中国经济的韧性得益于中国金融体系的韧性，可以抵抗外部的风险。一方面中国信用风险上升，但仍然处于较低水平；而中国商业银行不良贷款情况都能做到心中有数，“我们商业银行所有不良贷款都经过国际会计事务所审计，每个季度我们也在重检，因此商业银行的信用风险在可控范围内。”",
            "date_modified": "2021-03-20T13:08:38.000Z"
        },
        {
            "id": 2080319,
            "content_html": "",
            "url": "https://finance.sina.cn/7x24/2021-03-20/detail-ikkntiam5858773.d.html",
            "title": "【墨西哥开始为教练与运动员接种新冠疫苗以备战奥运】墨西哥18日开始为体育教练与运动员接种新冠疫苗，以更好地备战奥运会等国际赛事。墨西哥全国体育运动委员会当天发布公告说，当天上午，一些跳水和跆拳道教练及运动员完成第一剂新冠疫苗接种。当天参与接种的运动员计划代表墨西哥，出征东京奥运会与残奥会。",
            "date_modified": "2021-03-20T13:06:43.000Z"
        },
        {
            "id": 2080318,
            "content_html": "",
            "url": "https://finance.sina.cn/7x24/2021-03-20/detail-ikkntiam5858760.d.html",
            "title": "  比特币站上59500美元/枚，日内涨逾2.5%。",
            "date_modified": "2021-03-20T13:06:34.000Z"
        },
        {
            "id": 2080317,
            "content_html": "",
            "title": "【中国银行刘金:金融和实体背离 国际金融市场调整风险仍在加大】当前全球金融体系面临何种压力和风险？中国银行候任行长刘金在中国发展高层论坛上表示，全球金融体系面临的压力风险来自三个方面：第一，全球经济复苏的不确定性还比较强，经济可能长期陷入“低增长”的发展迷雾；第二个压力和风险是超宽松的货币政策带来全球高债务的困扰；第三个压力和风险是金融和实体背离，国际金融市场调整的风险仍然在加大。",
            "date_modified": "2021-03-20T13:06:20.000Z"
        },
        {
            "id": 2080315,
            "content_html": "",
            "url": "https://finance.sina.cn/7x24/2021-03-20/detail-ikknscsi9017589.d.html",
            "title": "【瑞银集团CEO：未来十年全球增长至少30%来自中国】瑞银集团首席执行官拉尔夫·哈默斯（Ralph Hamers）指出，未来十年全球增长至少30%将来自中国。中国人均可支配收入将继续增加。“对瑞银来说，去年我们获批了更多的合格境内机构投资者（QDII）额度。本月，我们进一步增持瑞银证券股权的计划也已正式启动。我们也将继续增加对中国这个令人振奋的市场的投入。” 哈默斯说。（澎湃）",
            "date_modified": "2021-03-20T13:03:08.000Z"
        },
        {
            "id": 2080314,
            "content_html": "",
            "url": "https://finance.sina.cn/7x24/2021-03-20/detail-ikkntiam5858200.d.html",
            "title": "【帮康美药业造假 广东正中珠江会计师事务所被罚没5700万】继证监会给予康美药业60万元的顶格处罚后，其审计机构“正中珠江”的处罚也已落地。因在康美药业审计业务中涉嫌违反相关法律法规，2019年广东正中珠江会计师事务所被证监会立案调查。2021年2月20日，证监会发布了对正中珠江的行政处罚决定书。处罚书中显示，证监会决定对正中珠江会计师事务所责令改正，罚没5700万元；对杨文蔚、张静璃、苏创升三人给予警告，并分别处以10万元罚款；对刘清给予警告，并处以3万元罚款。（证券时报网）",
            "date_modified": "2021-03-20T13:00:23.000Z"
        },
        {
            "id": 2080312,
            "content_html": "",
            "url": "https://finance.sina.cn/7x24/2021-03-20/detail-ikkntiam5857910.d.html",
            "title": "【高福：若世界不共享疫苗，病毒将共享世界】 3月20日，中国发展高层论坛2021年会“维护全球公共卫生安全”分论坛上，中国疾病控制预防中心主任高福表示，若世界不共享疫苗，病毒将共享世界。高福表示，病毒没有国籍、没有护照、说走就走，维护公共卫生安全是大家共同的事情。（澎湃）",
            "date_modified": "2021-03-20T12:56:26.000Z"
        },
        {
            "id": 2080311,
            "content_html": "",
            "title": "【王一鸣警示：美联储无限量宽松加剧全球流动性过剩】新任央行货币政策委员会委员王一鸣表示，美元是全球最重要的储备货币，美联储0到0.25的利率和无限量宽松政策加剧了全球的流动性过剩，短期资本大规模流入新兴市场，并推升本币的升值。美联储如果收紧货币政策，有可能导致新兴市场资本的大规模流出，资产价格的大幅下跌和金融市场的动荡。",
            "date_modified": "2021-03-20T12:53:31.000Z"
        },
        {
            "id": 2080310,
            "content_html": "",
            "url": "https://finance.sina.cn/7x24/2021-03-20/detail-ikkntiam5857505.d.html",
            "title": "媒体消息：EPIC游戏接近完成10亿美元融资，此次融资对该公司估值达280亿美元。",
            "date_modified": "2021-03-20T12:51:58.000Z"
        },
        {
            "id": 2080309,
            "content_html": "",
            "title": "【东莞控股：目前东莞证券IPO已经重启】东莞控股在互动平台表示，目前东莞证券IPO已经重启，具体进展请关注中国证监会网站。",
            "date_modified": "2021-03-20T12:51:21.000Z"
        },
        {
            "id": 2080308,
            "content_html": "",
            "url": "https://finance.sina.cn/7x24/2021-03-20/detail-ikkntiam5856873.d.html",
            "title": "【宝洁总裁数说中国消费市场】宝洁公司董事会主席、总裁兼首席执行官戴怀德20日在中国发展高层论坛2021经济峰会上点赞中国消费市场，并称中国消费者有其独特特点：①中国是世界上最大护肤品市场。②在北京和上海等大城市，中国女性护肤过程平均有4.7步，比全球平均值高3倍。③高端尿布已占中国尿布市场60%的份额。④宝洁服务全世界超50亿人，其中五分之一在中国。⑤宝洁已向中国推出65个品牌中的30个，但仍有约50%产品还未被中国消费者熟知。他表示，宝洁看好中国消费市场和创新环境，将继续扩大在华布局，更好服务中国消费者。（新华视点）",
            "date_modified": "2021-03-20T12:44:28.000Z"
        },
        {
            "id": 2080307,
            "content_html": "",
            "url": "https://finance.sina.cn/7x24/2021-03-20/detail-ikknscsi9015945.d.html",
            "title": "【日媒：东京奥运不接待海外观众预估损失超1500亿日元】据日本放送协会(NHK)报道，当地时间20日晚，由国际奥委会、国际残奥委会、东京奥组委、日本政府和东京都政府代表参加的五方会议一致决定，东京奥运会不会接待来自海外的普通观众。专家测算，此举将造成超1500亿日元的经济损失。不仅如此，木内还表示，如果海外观众退的票不能在日本国内再次销售的话，在票务方面可能还面临数百亿日元的损失。",
            "date_modified": "2021-03-20T12:43:11.000Z"
        },
        {
            "id": 2080306,
            "content_html": "",
            "title": "斯洛文尼亚新增新冠肺炎确诊病例1030例，累计确诊205509例；新增死亡病例6例，累计死亡4241例。",
            "date_modified": "2021-03-20T12:39:41.000Z"
        },
        {
            "id": 2080305,
            "content_html": "",
            "url": "https://finance.sina.cn/7x24/2021-03-20/detail-ikkntiam5856015.d.html",
            "title": "【泰国医药局长：将再向中国采购500万剂新冠疫苗】20日，泰国卫生部医药局长威吞•旦伟本在中国第二批疫苗抵达泰国的现场表示，泰国将再向中国采购500万剂新冠肺炎疫苗，以帮助泰国抗击新冠疫情的蔓延。泰国政府之前订购的中国科兴疫苗，将分三批抵达泰国。首批新冠疫苗已在2月24日抵达，并开始面向泰国民众进行疫苗接种工作；第二批新冠疫苗3月20日凌晨已运抵；第三批新冠疫苗将在4月抵达泰国。（央视新闻）",
            "date_modified": "2021-03-20T12:35:30.000Z"
        },
        {
            "id": 2080304,
            "content_html": "",
            "url": "https://finance.sina.cn/7x24/2021-03-20/detail-ikknscsi9015081.d.html",
            "title": "【中国疾控中心流行病学首席专家吴尊友：科学接种就是，让一个国家尽快达到70%-80%，再第二个国家】3月20日，在中国发展高层论坛2021年会上，中国疾控中心流行病学首席专家吴尊友发表演讲，指出几乎所有人对新冠病毒都是易感的，每个人都需要接种疫苗，每个人获得疫苗接种是一个基本人权问题。一个国家接种率没有达到70%，是起不到保护作用的。科学接种就是，让一个国家尽快达到70%-80%，再第二个国家、第三个国家达到。这样才能科学、有效地在全球实现群体免疫。（每经）",
            "date_modified": "2021-03-20T12:34:26.000Z"
        },
        {
            "id": 2080302,
            "content_html": "",
            "url": "https://finance.sina.cn/7x24/2021-03-20/detail-ikkntiam5855383.d.html",
            "title": "【香港各界支持完善选举制度 推动香港融入国家发展大局】连日来，香港多个社团举行两会精神宣讲会等活动，全面宣传解读完善特区选举制度决定的深刻内涵。他们认为，落实“爱国者治港”原则，推动香港融入国家发展大局，将为香港带来巨大发展机遇。（央视）",
            "date_modified": "2021-03-20T12:28:08.000Z"
        },
        {
            "id": 2080301,
            "content_html": "",
            "url": "https://finance.sina.cn/7x24/2021-03-20/detail-ikkntiam5855036.d.html",
            "title": "【美半导体行业协会总裁：政府应减少对芯片技术出口的限制】美国半导体行业协会（SIA）总裁兼CEO诺弗尔（John Neuffer）在中国发展高层论坛上表示，芯片行业高度依赖全球供应链，没有一个国家可以完全让芯片供应链自主化，政府应该减少对芯片技术出口的限制，加大对基础研究对投入，以推动半导体行业的创新。（一财）",
            "date_modified": "2021-03-20T12:23:55.000Z"
        },
        {
            "id": 2080300,
            "content_html": "",
            "url": "https://finance.sina.cn/7x24/2021-03-20/detail-ikkntiam5854715.d.html",
            "title": "【日本气象厅将宫城县地震震级修正为6.9级】当地时间20日晚，日本气象厅根据对宫城县的地震进行详细数据解析后，将地震震级从7.2级修正为6.9级，震源深度从60千米修正为59千米。（央视）",
            "date_modified": "2021-03-20T12:20:15.000Z"
        },
        {
            "id": 2080299,
            "content_html": "",
            "url": "https://finance.sina.cn/7x24/2021-03-20/detail-ikknscsi9013680.d.html",
            "title": "【第二批中国科兴新冠疫苗运抵泰国】由泰国向中国科兴公司订购的第二批新冠疫苗20日运抵泰国。20日清晨，泰国政府制药组织代表前往曼谷素万纳普机场接收这批疫苗。根据泰国卫生部与中国科兴公司签署的新冠疫苗订购协议，泰国向中方采购的新冠疫苗分三批交付，首批疫苗已于2月24日抵泰。",
            "date_modified": "2021-03-20T12:18:46.000Z"
        },
        {
            "id": 2080298,
            "content_html": "",
            "url": "https://finance.sina.cn/7x24/2021-03-20/detail-ikkntiam5854468.d.html",
            "title": "  印度财长西塔拉曼：印度正在寻找原油的替代资源。",
            "date_modified": "2021-03-20T12:17:49.000Z"
        },
        {
            "id": 2080297,
            "content_html": "",
            "url": "https://finance.sina.cn/7x24/2021-03-20/detail-ikkntiam5854287.d.html",
            "title": "【菲律宾日增新冠确诊病例创新高】菲律宾卫生部20日报告，当天该国新增新冠确诊病例7999例，创疫情暴发以来新高，累计确诊656056例；新增死亡病例30例，累计死亡12930例。近来，菲律宾新冠疫情呈快速反弹趋势，单日新增病例已连续多天超过4000例。",
            "date_modified": "2021-03-20T12:15:19.000Z"
        },
        {
            "id": 2080296,
            "content_html": "",
            "url": "https://finance.sina.cn/7x24/2021-03-20/detail-ikkntiam5854185.d.html",
            "title": "【持有人盈亏分布图曝光，近一年绝大多数追逐“顶流”基金经理的基民亏损】数据显示，近一年，绝大多数追逐“顶流”基金经理或者“网红”基金的基民都暂时陷入了亏损。例如，“公募一哥”张坤管理的易方达蓝筹精选近一年收益率超过118%，但近一年持有用户中，70%以上的投资者亏损幅度超过5%。（上证报）",
            "date_modified": "2021-03-20T12:13:54.000Z"
        },
        {
            "id": 2080295,
            "content_html": "",
            "url": "https://finance.sina.cn/7x24/2021-03-20/detail-ikkntiam5854027.d.html",
            "title": "【杨伟民：构建新格局需要深入持续地推进供给侧结构性改革】全国政协经济委员会副主任杨伟民在中国发展高层论坛2021年会上表示，构建新格局需要扩大内需，但也需要深入持续地推进供给侧结构性改革。目前中国国内的供给大于国内总需求，但也存在结构性的矛盾。比如生产型的、投资型的、出口型的产业规模比较大，但是居民消费型的产业比较少，这将从供给上制约居民消费扩大。现阶段很多消费型的产业供给难以满足居民需求，在供给侧需要进一步地去发展高技术产业、消费品产业、文化旅游产业。（证券时报）",
            "date_modified": "2021-03-20T12:12:25.000Z"
        },
        {
            "id": 2080294,
            "content_html": "",
            "url": "https://finance.sina.cn/7x24/2021-03-20/detail-ikkntiam5853731.d.html",
            "title": "日本新干线：东北新干线将于当地时间23:00（北京时间22:00）恢复运营。",
            "date_modified": "2021-03-20T12:09:50.000Z"
        },
        {
            "id": 2080293,
            "content_html": "",
            "url": "https://finance.sina.cn/7x24/2021-03-20/detail-ikkntiam5853637.d.html",
            "title": "【2021中国种子大会暨南繁硅谷论坛在海南三亚开幕】3月20日，由中国种子协会会同海南省相关部门等主办，以“种业使命 南繁未来”为主题的2021中国种子大会暨南繁硅谷论坛在三亚开幕，大会为期四天，议题涵盖水稻、玉米、蔬菜、南繁、种业知识产权保护、现代种业产业园和生命科学前沿等领域。（央视）",
            "date_modified": "2021-03-20T12:08:58.000Z"
        },
        {
            "id": 2080292,
            "content_html": "",
            "url": "https://finance.sina.cn/7x24/2021-03-20/detail-ikkntiam5853566.d.html",
            "title": "【迈克尔·斯宾塞：中国创新能力毋庸置疑 美国不具备中国的确定性】诺贝尔经济学奖获得者、纽约大学教授迈克尔·斯宾塞今天在参加中国发展高层论坛2021年会时表示，创新是中国“十四五”规划中的核心要素，毋庸置疑中国现在有能力做创新，可能十年前大家还在讨论这个话题，但过去十年中国的创新能力令人印象深刻，现在已没有任何怀疑。美国很难有中国这样的确定性，因为美国每四年就有总统选举，选出的新总统存在重拾四年前政策的可能性，这就很难做出像中国这样非常有确定性的、长期的规划。",
            "date_modified": "2021-03-20T12:08:06.000Z"
        },
        {
            "id": 2080291,
            "content_html": "",
            "url": "https://finance.sina.cn/7x24/2021-03-20/detail-ikknscsi9012694.d.html",
            "title": "【刘守英：农业需要有一场要素重组的革命】中国人民大学经济学院院长、教授刘守英在3月20日举办的中国发展高层论坛2021年会作主题演讲时表示，讨论乡村振兴越来越热了，而且弥漫着一种浪漫的情怀。但目前中国农村亟需扫除产业发展等方面的障碍。首先是土地的问题，其次是农业经营者的成长，第三是农业要素重组。",
            "date_modified": "2021-03-20T12:07:42.000Z"
        },
        {
            "id": 2080290,
            "content_html": "",
            "url": "https://finance.sina.cn/7x24/2021-03-20/detail-ikknscsi9012387.d.html",
            "title": "市场消息：华尔街正押注数十亿美颜押注电动汽车驱动的锂能源复苏，数据显示，曾因供应过剩而被避开的锂矿公司今年在美洲通过股票发行筹集了近34亿美元，这是自2018年至2020年筹集总额的7倍。",
            "date_modified": "2021-03-20T12:04:59.000Z"
        },
        {
            "id": 2080289,
            "content_html": "",
            "url": "https://finance.sina.cn/7x24/2021-03-20/detail-ikknscsi9012282.d.html",
            "title": "欧洲地中海地震中心：千岛群岛发生5.0级地震。",
            "date_modified": "2021-03-20T12:03:50.000Z"
        },
        {
            "id": 2080288,
            "content_html": "",
            "url": "https://finance.sina.cn/7x24/2021-03-20/detail-ikknscsi9012221.d.html",
            "title": "【2020年，我国钢铁行业生产、消费、效益均保持增长，今年1-2月继续保持增长态势】中国钢铁工业协会骆铁军副会长出席2021（第十二届）中国钢铁发展论坛指出，在刚刚过去的2020年，我国钢铁行业生产、消费、效益均保持增长，今年1-2月继续保持增长态势。总体看，我国钢铁行业运行稳中有进，高于预期，同时也面临一些问题。对此，钢协进行了研究，将“控产能不增，保有效供给；推铁矿投资，改定价机制；抓超低排放，寻低碳路径；行对标挖潜，稳企业效益”作为今年的重点工作。",
            "date_modified": "2021-03-20T12:03:00.000Z"
        },
        {
            "id": 2080287,
            "content_html": "",
            "url": "https://finance.sina.cn/7x24/2021-03-20/detail-ikkntiam5852580.d.html",
            "title": "阿斯利康将在未来数月内供应2.3亿剂新冠肺炎疫苗。",
            "date_modified": "2021-03-20T11:56:38.000Z"
        },
        {
            "id": 2080286,
            "content_html": "",
            "url": "https://finance.sina.cn/7x24/2021-03-20/detail-ikkntiam5852354.d.html",
            "title": "【世卫组织：全球新冠肺炎确诊病例超过1.217亿例】根据世卫组织最新实时统计数据，截至欧洲中部时间3月20日9时35分（北京时间3月20日16时35分），全球累计确诊新冠肺炎病例121759109例，累计死亡2690731例。",
            "date_modified": "2021-03-20T11:53:51.000Z"
        },
        {
            "id": 2080285,
            "content_html": "",
            "url": "https://finance.sina.cn/7x24/2021-03-20/detail-ikkntiam5852290.d.html",
            "title": "  市场消息：阿斯利康将在数月内通过新冠肺炎疫苗实施计划（COVAX）提供2.3亿剂疫苗。",
            "date_modified": "2021-03-20T11:53:02.000Z"
        },
        {
            "id": 2080284,
            "content_html": "",
            "url": "https://finance.sina.cn/7x24/2021-03-20/detail-ikkntiam5852278.d.html",
            "title": "【印尼特里嘎那航空公司一架飞机冲出跑道 暂无人员伤亡】当地时间3月20日，印度尼西亚雅加达哈利姆机场执行总经理马司玛（Marsma Nandang Sukarna）介绍说，一架特里嘎那航空公司飞机的发动机出现故障，该飞机在着陆时冲出了跑道。目前没有收到人员伤亡的消息。（央视）",
            "date_modified": "2021-03-20T11:52:51.000Z"
        },
        {
            "id": 2080282,
            "content_html": "",
            "url": "https://finance.sina.cn/7x24/2021-03-20/detail-ikknscsi9011015.d.html",
            "title": "  【吴尊友：老龄化严重的国家应最先通过新冠疫苗实现群体免疫】中国疾病预防控制中心流行病学首席专家吴尊友表示，如果每个国家都以相同覆盖率往上走，没有达到百分之七八十时，百分十二三十都是达不到作用的。要科学有效地在全球推广疫苗接种，而不是全世界所有国家齐步走往前推进。高年龄组的国家，也就是老龄化严重的国家，应该是最先实现群体免疫的国家。（澎湃）",
            "date_modified": "2021-03-20T11:47:50.000Z"
        },
        {
            "id": 2080281,
            "content_html": "",
            "url": "https://finance.sina.cn/7x24/2021-03-20/detail-ikkntiam5851723.d.html",
            "title": "【天津市新增2例境外输入确诊病例】据“健康天津”微信公众号消息，3月19日18时至20日18时，天津市新增2例境外输入新冠肺炎确诊病例（由无症状感染者转归），累计报告境外输入确诊病例223例。",
            "date_modified": "2021-03-20T11:46:01.000Z"
        },
        {
            "id": 2080280,
            "content_html": "",
            "url": "https://finance.sina.cn/7x24/2021-03-20/detail-ikknscsi9010731.d.html",
            "title": "  比特币短线拉升约400美元，最高至59244美元/枚。",
            "date_modified": "2021-03-20T11:43:58.000Z"
        },
        {
            "id": 2080279,
            "content_html": "",
            "url": "https://finance.sina.cn/7x24/2021-03-20/detail-ikkntiam5851528.d.html",
            "title": "【3月20日《新闻联播》主要内容】今天《新闻联播》主要内容有：1、【在习近平新时代中国特色社会主义思想指引下——贯彻新发展理念 推动高质量发展】湖南：创新发展 推进产业结构优化升级；2、【新征程开局“十四五”】完善养老服务体系 绘制老有所养新蓝图；3、党史学习教育中央宣讲团在河北、内蒙古、湖北举行报告会；4、春分至 绿色春耕力促粮食稳产提质；5、三星堆遗址考古发掘取得重大进展；6、中国发展高层论坛2021年会今天举行；7、香港各界支持完善选举制度 推动香港融入国家发展大局；8、北京：接种新冠疫苗超千万剂次；9、国家卫生健康委通报最新疫情；10、中国代表：美国在涉疆问题上痴迷于制造谎言；11、全球新冠肺炎确诊病例超1亿2146万例；12、东京奥运会将不接待国外观众；13、日本宫城县海域发生7.2级地震 东京有震感。",
            "date_modified": "2021-03-20T11:43:20.000Z"
        },
        {
            "id": 2080278,
            "content_html": "",
            "url": "https://finance.sina.cn/7x24/2021-03-20/detail-ikkntiam5851479.d.html",
            "title": "日本气象厅JMA：日本地震震级从7.2级修正为6.9级，震源深度从60千米修正为59千米。",
            "date_modified": "2021-03-20T11:42:43.000Z"
        },
        {
            "id": 2080277,
            "content_html": "",
            "url": "https://finance.sina.cn/7x24/2021-03-20/detail-ikknscsi9010356.d.html",
            "title": "【宝洁总裁：相信中国将会成为世界上最大、最先进的消费市场】3月20日，中国发展高层论坛2021年会“释放消费新势能分论坛”上，宝洁公司全球董事会主席、总裁兼首席执行官戴怀德称，“宝洁相信中国将会成为世界上最大、最复杂及最先进的消费市场。”他表示，现在宝洁服务全世界超过50亿人，其中五分之一是在中国。据戴怀德介绍，中国已经成为世界上最大的护肤市场，并且也有着最复杂的消费者。（澎湃）",
            "date_modified": "2021-03-20T11:39:45.000Z"
        },
        {
            "id": 2080276,
            "content_html": "",
            "url": "https://finance.sina.cn/7x24/2021-03-20/detail-ikknscsi9010068.d.html",
            "title": "【我国新冠疫苗接种达7000万人次】3月20日，由中华预防医学会主办的“新形势，新起点——新冠疫情下免疫策略交流大会”在京举办。国家卫健委疾控局二级巡视员崔钢在会上披露，截至目前，我国新冠疫苗接种已经达到7000万人次。中国疾控中心主任高福院士在会上称：“未来新冠与流感叠加流行也将成为疫情防控的重要挑战，在新冠疫苗接种全面推进的过程中，我国流感疫苗接种率长期低下的局面也亟须改观。”（北京日报）",
            "date_modified": "2021-03-20T11:36:18.000Z"
        },
        {
            "id": 2080275,
            "content_html": "",
            "url": "https://finance.sina.cn/7x24/2021-03-20/detail-ikknscsi9009840.d.html",
            "title": "【国际清算银行总经理：各央行有应对通胀的工具】国际清算银行总经理Agustin Carstens表示，在推出前所未有的疫情刺激措施后，全球央行拥有应对通货膨胀率上升的工具。“通货膨胀率可能会激增”，Carstens表示，这将需要包括美联储在内的央行调整货币政策，并更加重视实现充分就业的目标。美联储将“极为警惕”，通货膨胀“不会成为破坏稳定的因素”。",
            "date_modified": "2021-03-20T11:33:47.000Z"
        },
        {
            "id": 2080274,
            "content_html": "",
            "url": "https://finance.sina.cn/7x24/2021-03-20/detail-ikknscsi9009729.d.html",
            "title": "【黑龙江省气象台发布暴雪黄色预警信号】黑龙江省气象台2021年3月20日17时45分发布暴雪黄色预警信号：预计未来12小时，伊春东部、哈尔滨东部、鹤岗、佳木斯、双鸭山、七台河、鸡西、牡丹江降雪量将达6毫米以上，降雪同时伴有4～6级风，阵风7级，有风吹雪，局地可能出现雪阻，能见度低，请注意预防。（央视）",
            "date_modified": "2021-03-20T11:32:17.000Z"
        },
        {
            "id": 2080272,
            "content_html": "",
            "url": "https://finance.sina.cn/7x24/2021-03-20/detail-ikknscsi9009352.d.html",
            "title": "东京奥组委首席执行官武藤敏郎：我们不会公布退款的金额。",
            "date_modified": "2021-03-20T11:27:40.000Z"
        },
        {
            "id": 2080271,
            "content_html": "",
            "url": "https://finance.sina.cn/7x24/2021-03-20/detail-ikknscsi9009323.d.html",
            "title": "东京奥组委首席执行官武藤敏郎：将在4月的五方会议后决定奥运会是否接待国内观众。",
            "date_modified": "2021-03-20T11:27:12.000Z"
        },
        {
            "id": 2080270,
            "content_html": "",
            "url": "https://finance.sina.cn/7x24/2021-03-20/detail-ikkntiam5849541.d.html",
            "title": "【香港新增8例新冠肺炎确诊病例】香港特区政府卫生署卫生防护中心20日公布，截至当日零时，香港新增8例新冠肺炎确诊病例，其中有7例本土感染病例。香港累计报告新冠肺炎确诊病例达11371例。这是自3月10日以来，香港单日新增确诊病例数首次回落至个位数。（新华网）",
            "date_modified": "2021-03-20T11:20:49.000Z"
        },
        {
            "id": 2080269,
            "content_html": "",
            "url": "https://finance.sina.cn/7x24/2021-03-20/detail-ikknscsi9008414.d.html",
            "title": "东京奥组委首席执行官武藤敏郎：可能会考虑削减参加奥运会的工作人员数量。",
            "date_modified": "2021-03-20T11:16:59.000Z"
        },
        {
            "id": 2080268,
            "content_html": "",
            "url": "https://finance.sina.cn/7x24/2021-03-20/detail-ikkntiam5848932.d.html",
            "title": "  东京奥组委首席执行官武藤敏郎：退票项目将不包括海外观众的酒店预订费用。",
            "date_modified": "2021-03-20T11:13:49.000Z"
        },
        {
            "id": 2080266,
            "content_html": "",
            "url": "https://finance.sina.cn/7x24/2021-03-20/detail-ikknscsi9008162.d.html",
            "title": "  东京奥组委首席执行官武藤敏郎：将退还约60万张奥运会门票和3万张残奥会门票。",
            "date_modified": "2021-03-20T11:13:34.000Z"
        },
        {
            "id": 2080265,
            "content_html": "",
            "url": "https://finance.sina.cn/7x24/2021-03-20/detail-ikkntiam5848683.d.html",
            "title": "  国务院办公厅关于调整中国人民银行货币政策委员会组成人员的通知：同意蔡昉、王一鸣担任货币政策委员会委员，刘世锦继续担任货币政策委员会委员，刘伟、马骏不再担任货币政策委员会委员职务。",
            "date_modified": "2021-03-20T11:11:06.000Z"
        },
        {
            "id": 2080263,
            "content_html": "",
            "url": "https://finance.sina.cn/7x24/2021-03-20/detail-ikknscsi9007714.d.html",
            "title": "【全国人大社会建设委员会副主任委员江小涓：以数字发展带动经济发展】 全国人大社会建设委员会副主任委员、清华大学公共管理学院院长江小涓3月20日在中国发展高层论坛2021年会上表示，“我国数字经济有广阔的发展空间，在全球经济中也有非常良好的起点。”江小涓表示，未来五年数字消费将出现重量级应用，数字生产进入加速阶段，数字资源的开发利用会快速推进。（中证报）",
            "date_modified": "2021-03-20T11:09:37.000Z"
        },
        {
            "id": 2080262,
            "content_html": "",
            "url": "https://finance.sina.cn/7x24/2021-03-20/detail-ikkntiam5847921.d.html",
            "title": "英国卫生大臣汉考克：目前英国有一半的成年人都接种了新冠疫苗。",
            "date_modified": "2021-03-20T11:04:32.000Z"
        },
        {
            "id": 2080261,
            "content_html": "",
            "url": "https://finance.sina.cn/7x24/2021-03-20/detail-ikkntiam5847812.d.html",
            "title": "【高通CEO：汽车芯片需要时间出货，通信芯片以后要更多功能】高通公司CEO史蒂夫·莫伦科夫说：“现在，汽车芯片短缺是广泛存在的问题，市场其实可以更快地去反应，一些新兴的技术可能反应相对较慢，我们一直在看到一些改进，但是我们还是需要时间去出货、供给。”当话题转到通信芯片的下一步发展趋势时，史蒂夫·莫伦科夫表示，通信芯片的趋势是要整合更多的功能，体积更小，能够处理更多的信息，能够存储在本地设备上，而不需要把信息更多地上传到云端。（澎湃）",
            "date_modified": "2021-03-20T11:03:29.000Z"
        },
        {
            "id": 2080259,
            "content_html": "",
            "url": "https://finance.sina.cn/7x24/2021-03-20/detail-ikkntiam5847254.d.html",
            "title": "【工信部副部长刘烈宏：我国将培养一批产业链“链主”企业】中国工业和信息化部党组成员、副部长刘烈宏表示，“十四五”期间将发挥优质企业的作用，培养一批具有生态主导力的产业链“链主”企业，促进大中小企业融通发展。据了解，工信部将落实各项稳企政策，着力增强企业的活力和实力，支持企业做强做优。还将支持中小企业做专做精，在产业优势领域精耕细作、提供更多独门绝技，促进大中小企业融通发展。（财经杂志）",
            "date_modified": "2021-03-20T10:57:18.000Z"
        },
        {
            "id": 2080258,
            "content_html": "",
            "url": "https://finance.sina.cn/7x24/2021-03-20/detail-ikkntiam5846962.d.html",
            "title": "【瑞信首席执行官：计划一年内实现合资证券公司100%持股】3月20日，中国发展高层论坛2021年会上，瑞信集团首席执行官高曦泰 （Thomas Gottstein）表示，中国和亚太地区是瑞信集团非常重要的市场，约占到集团总收入的20%。高曦泰称，未来将继续扩大瑞信集团在中国的业务，未来三年里将继续增强集团在中国的地位。“我们最近收购了合资证券公司51%的股份，计划在未来一年内将其持股比例增到100%。”（澎湃）",
            "date_modified": "2021-03-20T10:53:25.000Z"
        },
        {
            "id": 2080257,
            "content_html": "",
            "url": "https://finance.sina.cn/7x24/2021-03-20/detail-ikknscsi9005678.d.html",
            "title": "【因强降雨天气 澳大利亚最大规模的城市供水水库开始溢水】当地时间20日16时左右，位于澳大利亚悉尼以西约70公里的沃勒甘巴水库已经达到最大储水值，并开始溢水。这是自2016年以来，该水库首次出现溢水现象。（央视）",
            "date_modified": "2021-03-20T10:47:16.000Z"
        },
        {
            "id": 2080256,
            "content_html": "",
            "url": "https://finance.sina.cn/7x24/2021-03-20/detail-ikknscsi9005527.d.html",
            "title": "  【国际奥委会等五方正式宣布：东京奥运会将不接待国外观众】 3月20日晚，东京奥组委与国际奥委会等五方举行会谈后正式宣布，今年夏季的东京奥运会及残奥会不接待国外观众。",
            "date_modified": "2021-03-20T10:45:18.000Z"
        },
        {
            "id": 2080255,
            "content_html": "",
            "url": "https://finance.sina.cn/7x24/2021-03-20/detail-ikknscsi9005247.d.html",
            "title": "东京奥组委：海外观众将不能在奥运会期间进入日本观赛，其购买的奥运会和残奥会门票将被退还。",
            "date_modified": "2021-03-20T10:41:46.000Z"
        },
        {
            "id": 2080253,
            "content_html": "",
            "url": "https://finance.sina.cn/7x24/2021-03-20/detail-ikkntiam5845325.d.html",
            "title": "【沙尘暴蓝色预警继续，全国13省区仍有扬沙和浮尘】中央气象台3月20日18时继续发布沙尘暴蓝色预警：受冷空气大风影响，预计3月20日20时至21日20时，新疆东部和南疆盆地、青海北部、甘肃南部、陕西中部、山西南部、河北西北部和南部、山东西部、河南、安徽北部、湖北中部、湖南北部、四川盆地西部、内蒙古中部等地的部分地区有扬沙或浮尘天气，其中，新疆东北部局地有沙尘暴。（央视）",
            "date_modified": "2021-03-20T10:35:28.000Z"
        },
        {
            "id": 2080252,
            "content_html": "",
            "url": "https://finance.sina.cn/7x24/2021-03-20/detail-ikknscsi9004521.d.html",
            "title": "国际奥委会表示，日本地震不再有海啸威胁。",
            "date_modified": "2021-03-20T10:34:26.000Z"
        },
        {
            "id": 2080251,
            "content_html": "",
            "url": "https://finance.sina.cn/7x24/2021-03-20/detail-ikkntiam5845175.d.html",
            "title": "日本放送协会NHK：日本宫城县的海啸预警已解除。",
            "date_modified": "2021-03-20T10:34:03.000Z"
        },
        {
            "id": 2080250,
            "content_html": "",
            "url": "https://finance.sina.cn/7x24/2021-03-20/detail-ikkntiam5845125.d.html",
            "title": "市场消息：因物流问题，阿斯利康疫苗推迟到下周送达意大利。",
            "date_modified": "2021-03-20T10:33:29.000Z"
        },
        {
            "id": 2080248,
            "content_html": "",
            "url": "https://finance.sina.cn/7x24/2021-03-20/detail-ikkntiam5844573.d.html",
            "title": "【中国地震台网：今年以来全球共发生6级以上地震39次，7级以上达7次】 今年以来，全球共发生六级以上地震39次，其中6.0级到6.9级32次，7.0级到7.9级7次，8.0级以上0次，最大地震是3月5日在新西兰克马德克群岛发生的7.8级地震。",
            "date_modified": "2021-03-20T10:26:24.000Z"
        },
        {
            "id": 2080247,
            "content_html": "",
            "url": "https://finance.sina.cn/7x24/2021-03-20/detail-ikknscsi9003898.d.html",
            "title": "【一个月前刚完成A轮的蜂巢能源已启动B轮融资，预计融资30-40亿元】据悉，蜂巢能源科技有限公司正在进行B轮融资，本轮融资金额预计30-40亿元。B轮融资之后，蜂巢能源将启动IPO工作，预计2022年申报科创板。蜂巢能源是一家专业从事汽车动力电池材料、电芯、模组、PACK、BMS、储能、太阳能研发和制造的新能源科技公司，前身是长城汽车动力电池事业部，2018年2月从长城汽车独立。",
            "date_modified": "2021-03-20T10:26:11.000Z"
        },
        {
            "id": 2080246,
            "content_html": "",
            "url": "https://finance.sina.cn/7x24/2021-03-20/detail-ikknscsi9003210.d.html",
            "title": "【今年前两个月我国预焙阳极出口总量约为26.85万吨】据海关数据统计，2021年1-2月份我国预焙阳极出口总量约为26.85万吨，同比增长15.7%，其中一月份出口总量约为13.34万吨，环比2020年12月减少11.3%；二月份出口总量约为13.51万吨。1-2月份预焙阳极出口总金额约为1.58亿美元。",
            "date_modified": "2021-03-20T10:18:40.000Z"
        },
        {
            "id": 2080245,
            "content_html": "",
            "url": "https://finance.sina.cn/7x24/2021-03-20/detail-ikknscsi9003126.d.html",
            "title": "【工商银行董事长陈四清：经济运行稳中向好 为防范金融风险营造良好环境】中国工商银行董事长陈四清3月20日在中国发展高层论坛2021年会上表示，今年以来，经济运行延续稳中向好的态势，积极因素持续增多，为防范和化解金融风险营造了良好的经济环境。“经济兴、金融兴，经济强、金融强，我国经济能够保持稳健发展态势，为金融业的对外开放提供了良好的外部环境。同时金融业加快开放，也为经济的高质量发展提供了新动能。”",
            "date_modified": "2021-03-20T10:17:33.000Z"
        },
        {
            "id": 2080244,
            "content_html": "",
            "url": "https://finance.sina.cn/7x24/2021-03-20/detail-ikkntiam5843636.d.html",
            "title": "日本东北电力公司：仙台核电站的燃气发电组暂停运行。",
            "date_modified": "2021-03-20T10:16:02.000Z"
        },
        {
            "id": 2080243,
            "content_html": "",
            "url": "https://finance.sina.cn/7x24/2021-03-20/detail-ikknscsi9002894.d.html",
            "title": "据媒体消息：德国希望延长复兴信贷银行的疫情特殊援助项目。",
            "date_modified": "2021-03-20T10:14:17.000Z"
        },
        {
            "id": 2080242,
            "content_html": "",
            "url": "https://finance.sina.cn/7x24/2021-03-20/detail-ikkntiam5843466.d.html",
            "title": "【年内6省市出台租赁政策，多家长租公寓入住率超90%】据了解，随着疫情的控制，整个租赁市场正在快速回暖，目前多家长租公寓的入住率都已超过90%。上海自如总经理张远鹏称，全国成交量都有30%以上涨幅的情况，上海达到了92%以上出租的效率。今年2月以来，已有北京、上海、广州、深圳等6个省市先后出台关于房屋租赁的政策。（央视财经）",
            "date_modified": "2021-03-20T10:14:01.000Z"
        },
        {
            "id": 2080241,
            "content_html": "",
            "url": "https://finance.sina.cn/7x24/2021-03-20/detail-ikkntiam5842757.d.html",
            "title": "  【IMF拟上调2021年日美经济增长率预期】关于国际货币基金组织（IMF）将于4月发布的最新《世界经济展望》，20日获悉正在朝着上调日本和美国2021年增长率的方向展开协调。美国总额1.9万亿美元的经济对策将强力提振全球经济。这将是IMF继1月的上次预测之后再度上调，或给人以经济从新冠疫情中复苏的印象。",
            "date_modified": "2021-03-20T10:07:07.000Z"
        },
        {
            "id": 2080240,
            "content_html": "",
            "url": "https://finance.sina.cn/7x24/2021-03-20/detail-ikkntiam5842737.d.html",
            "title": "瑞士信贷计划将中国员工人数增加两倍以上。",
            "date_modified": "2021-03-20T10:06:57.000Z"
        },
        {
            "id": 2080238,
            "content_html": "",
            "url": "https://finance.sina.cn/7x24/2021-03-20/detail-ikkntiam5842186.d.html",
            "title": "立讯精密：公司生产经营情况正常，关于2020年度经营业绩的预计情况已于公司《2020年第三季度报告》中披露，目前不存在需调整的情况。公司始终秉承股东及公司利益最大化原则，致力于做好经营管理工作。",
            "date_modified": "2021-03-20T10:00:58.000Z"
        },
        {
            "id": 2080236,
            "content_html": "",
            "url": "https://finance.sina.cn/7x24/2021-03-20/detail-ikknscsi9001394.d.html",
            "title": "  据日本共同社：女川核电站没有异常情况。",
            "date_modified": "2021-03-20T09:57:25.000Z"
        },
        {
            "id": 2080235,
            "content_html": "",
            "url": "https://finance.sina.cn/7x24/2021-03-20/detail-ikknscsi9001297.d.html",
            "title": "据媒体消息：福岛第一核电站和东海第二核电站没有异常情况。",
            "date_modified": "2021-03-20T09:55:57.000Z"
        },
        {
            "id": 2080234,
            "content_html": "",
            "title": "据日本放送协会NHK：日本气象厅JMA将于当地时间20:10（北京时间19:10）就地震召开新闻发布会。",
            "date_modified": "2021-03-20T09:53:43.000Z"
        },
        {
            "id": 2080233,
            "content_html": "",
            "url": "https://finance.sina.cn/7x24/2021-03-20/detail-ikknscsi9000949.d.html",
            "title": "据日本共同社：日本核燃料公司表示六所核电站没有出现异常。",
            "date_modified": "2021-03-20T09:51:15.000Z"
        },
        {
            "id": 2080232,
            "content_html": "",
            "url": "https://finance.sina.cn/7x24/2021-03-20/detail-ikknscsi9000724.d.html",
            "title": "据TBS电视台：东北电力公司正在检查女川核电站是否异常。",
            "date_modified": "2021-03-20T09:48:57.000Z"
        },
        {
            "id": 2080231,
            "content_html": "",
            "url": "https://finance.sina.cn/7x24/2021-03-20/detail-ikkntiam5841124.d.html",
            "title": "  巴基斯坦总理健康顾问Sultan表示，总理正在家中隔离。",
            "date_modified": "2021-03-20T09:48:17.000Z"
        },
        {
            "id": 2080230,
            "content_html": "",
            "url": "https://finance.sina.cn/7x24/2021-03-20/detail-ikkntiam5840844.d.html",
            "title": "丹麦首都区报告出现两例医院工作人员在接种阿斯利康疫苗后出现血凝块、脑出血的病例，并表示一名医院工作人员已经死亡。",
            "date_modified": "2021-03-20T09:45:06.000Z"
        },
        {
            "id": 2080229,
            "content_html": "",
            "url": "https://finance.sina.cn/7x24/2021-03-20/detail-ikkntiam5840555.d.html",
            "title": "【中欧班列（武汉）首次延伸至意大利米兰】满载湖北企业生产的电子产品、汽车零配件、防疫物资等的X8015次列车20日清晨从武汉吴家山站开出，驶往德国杜伊斯堡。这趟列车的部分车皮及其装载的货物还将从杜伊斯堡前往意大利米兰，标志着中欧班列（武汉）首次延伸到意大利米兰。",
            "date_modified": "2021-03-20T09:42:46.000Z"
        },
        {
            "id": 2080228,
            "content_html": "",
            "url": "https://finance.sina.cn/7x24/2021-03-20/detail-ikknscsi9000071.d.html",
            "title": "据媒体消息：日本东北新干线因地震暂停运行。",
            "date_modified": "2021-03-20T09:42:18.000Z"
        },
        {
            "id": 2080227,
            "content_html": "",
            "url": "https://finance.sina.cn/7x24/2021-03-20/detail-ikkntiam5840189.d.html",
            "title": "日本东北电力公司：日本宫城县部分地区遭遇停电。",
            "date_modified": "2021-03-20T09:39:59.000Z"
        },
        {
            "id": 2080225,
            "content_html": "",
            "url": "https://finance.sina.cn/7x24/2021-03-20/detail-ikknscsi8999752.d.html",
            "title": "据日本放送协会NHK：海啸预计在日本时间18:40（北京时间17:40）左右抵达宫城县仙台港。",
            "date_modified": "2021-03-20T09:39:16.000Z"
        },
        {
            "id": 2080217,
            "content_html": "",
            "url": "https://finance.sina.cn/7x24/2021-03-20/detail-ikkntiam5839750.d.html",
            "title": "  巴基斯坦卫生部长：巴基斯坦总理的新冠病毒检测呈阳性。",
            "date_modified": "2021-03-20T09:34:08.000Z"
        },
        {
            "id": 2080216,
            "content_html": "",
            "url": "https://finance.sina.cn/7x24/2021-03-20/detail-ikkntiam5839740.d.html",
            "title": "【夏光：碳达峰政策驱动力可以分解为推动力、拉动力、行动力】生态环境部研究员夏光表示，总体上来讲，我们可以把碳达峰政策驱动力分解为三个方面，就是三大动力叫做推动力、拉动力、行动力这三者。第一关于推动力就是由政府来实施管制性的政策。在完成以后，各级政府在实施制定高碳低碳产业的目录，提出产品的碳标签，限制高能耗高排放产业的发展等等以及交通行业其他行业的将他要求这是推动力。第三个就是行动力，行动力就是要增强社会的行动能力这一类的政策。要采取更多的鼓励性的政策，采取节鼓励公众节约能源，合理丧失垃圾分类，低碳出行，公共交通、循环利用、美化家庭等等各种各样的方式来改善我们的生活，而是用低碳节约的方式来形成我们新的生活方式。",
            "date_modified": "2021-03-20T09:34:03.000Z"
        },
        {
            "id": 2080215,
            "content_html": "",
            "url": "https://finance.sina.cn/7x24/2021-03-20/detail-ikknscsi8999177.d.html",
            "title": "据媒体消息：东京电力公司正在检查福岛第一核电站的异常情况。",
            "date_modified": "2021-03-20T09:32:25.000Z"
        },
        {
            "id": 2080214,
            "content_html": "",
            "url": "https://finance.sina.cn/7x24/2021-03-20/detail-ikkntiam5839274.d.html",
            "title": "【百亿级私募最新持仓情况汇总！高瓴礼仁加仓上海机电，高毅邓晓峰继续减持紫金矿业】从近期密集披露的上市公司年报来看，去年四季度，高瓴旗下的礼仁投资继续加仓上海机电；颜克益的大朴资产对军工行业有所布局，新进入贵航股份前十大股东名单；而高毅资产首席投资官邓晓峰继续小幅减仓紫金矿业，他管理的两只产品合计持股数量减少了超2600万股。",
            "date_modified": "2021-03-20T09:28:22.000Z"
        },
        {
            "id": 2080213,
            "content_html": "",
            "url": "https://finance.sina.cn/7x24/2021-03-20/detail-ikknscsi8998459.d.html",
            "title": "日本宫城县附近海域发生里氏7.2级地震，东京有震感。日本气象厅发布海啸警报。（人民日报）",
            "date_modified": "2021-03-20T09:24:30.000Z"
        },
        {
            "id": 2080212,
            "content_html": "",
            "url": "https://finance.sina.cn/7x24/2021-03-20/detail-ikknscsi8998186.d.html",
            "title": "  日本放送协会NHK警告居民称，海啸预计将有1米高，不要靠近海岸。",
            "date_modified": "2021-03-20T09:23:09.000Z"
        },
        {
            "id": 2080211,
            "content_html": "",
            "url": "https://finance.sina.cn/7x24/2021-03-20/detail-ikknscsi8997310.d.html",
            "title": "【陈四清：金融机构要以高质量风控推动高质量发展】3月20日，中国工商银行董事长陈四清在中国发展高层论坛2021年会上表示，要增加系统管理，以高质量风控推动高质量的开放，金融机构要强化风险管理的能力，提高风险的治理能力，提升应急管理的能力，银行要实现可持续发展需要付出更大的努力。陈四清指出，中国经济稳中向好，为金融业的开放提供了良好的环境。过去的中国经济克服了疫情和全球经济体衰退的影响，今年以来，经济运行持续稳中向好的态势，积极因素增多，为防范和化解金融风险提供了良好的空间。我国经济持续稳健的态势为金融业的对外开放提供了外部环境，金融业的对外开放也为经济发展提供的新的动能。（证券时报网）",
            "date_modified": "2021-03-20T09:18:37.000Z"
        },
        {
            "id": 2080210,
            "content_html": "",
            "url": "https://finance.sina.cn/7x24/2021-03-20/detail-ikkntiam5837621.d.html",
            "title": "【德国新增新冠肺炎确诊病例16033例 累计确诊2645783例】据德国联邦疾控机构罗伯特·科赫研究所公布的数据，截至当地时间3月20日0时，过去24小时，德国新增新冠肺炎确诊病例16033例，累计确诊2645783例，累计死亡74565例。（央视）",
            "date_modified": "2021-03-20T09:17:26.000Z"
        },
        {
            "id": 2080209,
            "content_html": "",
            "url": "https://finance.sina.cn/7x24/2021-03-20/detail-ikkntiam5837242.d.html",
            "title": "【海南省常务副省长沈丹阳：大力发展离岛免税购物】海南省常务副省长沈丹阳20日在中国发展高层论坛2021年会上表示，按照中央对海南的定位，海南正在加快构建旅游业、现代服务业、高新技术产业以及热带特色高效农业的现代产业体系，这里面蕴含着大量的投资机会。",
            "date_modified": "2021-03-20T09:15:03.000Z"
        },
        {
            "id": 2080208,
            "content_html": "",
            "url": "https://finance.sina.cn/7x24/2021-03-20/detail-ikknscsi8996622.d.html",
            "title": "  据日本放送协会NHK：日本发生里氏7.2级地震，针对宫城县发布海啸预警。",
            "date_modified": "2021-03-20T09:14:23.000Z"
        },
        {
            "id": 2080207,
            "content_html": "",
            "url": "https://finance.sina.cn/7x24/2021-03-20/detail-ikkntiam5836975.d.html",
            "title": "日本气象厅JMA：日本宫城县附近发生地震，地震导致东京建筑物摇晃。",
            "date_modified": "2021-03-20T09:13:40.000Z"
        },
        {
            "id": 2080206,
            "content_html": "",
            "url": "https://finance.sina.cn/7x24/2021-03-20/detail-ikkntiam5836580.d.html",
            "title": "【市值6亿元的迷你ST公司迎新掌门，退市新规留“活路”？】业绩大概率连续三年亏损、市值仅6亿元，这样经营惨淡的ST公司也“不愁嫁”？据3月19日公告，原“长城系”三驾马车之一的*ST长动迎来新的董事长。这意味着，今年2月通过表决权委托方式入主的山西振兴生物药业有限公司正式掌控了*ST长动董事会。走马上任的新任董事长为任彦堂，曾任振兴集团财务副总经理、振兴生物监事。权力更替的局面早已定下。今年2月8日，*ST长动的控股股东浙江清风原生文化有限公司及其一致行动人赵锐勇与振兴生物签署《表决权委托协议》。（上证报）",
            "date_modified": "2021-03-20T09:11:23.000Z"
        },
        {
            "id": 2080205,
            "content_html": "",
            "url": "https://finance.sina.cn/7x24/2021-03-20/detail-ikknscsi8996042.d.html",
            "title": "【北向资金本周扫货重点曝光，格力电器获加仓超26亿元】本周北向资金净流入87.08亿元，其中沪股通净流入6.76亿元，深股通净流入80.32亿元。净买入额居前三的股票是格力电器、三一重工、隆基股份，净买入额分别为26.31亿元、9.41亿元、9.33亿元。本周净卖出额居前三的股票是贵州茅台、泸州老窖、中国平安，净卖出额分别为23.13亿元、9.08亿元、7.41亿元。（一财）",
            "date_modified": "2021-03-20T09:11:03.000Z"
        },
        {
            "id": 2080204,
            "content_html": "",
            "url": "https://finance.sina.cn/7x24/2021-03-20/detail-ikknscsi8995601.d.html",
            "title": "【麦肯锡：碳中和背景下，中国10年内对氢能的需求或将增至1800万】麦肯锡公司董事长、全球总裁施南德表示：根据麦肯锡的研究，中国对氢气的需求现在近乎为零，但到2030年或将增至1800万，主要来自钢铁和运输行业。（一财）",
            "date_modified": "2021-03-20T09:08:52.000Z"
        },
        {
            "id": 2080202,
            "content_html": "",
            "url": "https://finance.sina.cn/7x24/2021-03-20/detail-ikkntiam5835543.d.html",
            "title": "【美国迈阿密海滩人群扎堆 警方动用胡椒喷雾驱散人群】当前美国各大院校仍值春假期间，很多人无视疫情扎堆过春假。18日，佛罗里达州迈阿密海滩附近就聚集了大批过春假的人群，当地不得不出动警力并使用胡椒喷雾才将人群驱散。（央视）",
            "date_modified": "2021-03-20T09:04:12.000Z"
        }
    ]
}