{
    "version": "https://jsonfeed.org/version/1",
    "title": "新浪新闻",
    "home_page_url": "https://pluckhuang.github.io/realtime-news/",
    "feed_url": "https://pluckhuang.github.io/realtime-news/rss.json",
    "description": "新浪全球实时财经新闻直播",
    "items": [
        {
            "id": 2136339,
            "content_html": "",
            "url": "https://finance.sina.cn/7x24/2021-04-22/detail-ikmxzfmk8366852.d.html",
            "title": "陶氏化学(DOW.N)：预计经济复苏范围扩大，将继续令合资企业受益。",
            "date_modified": "2021-04-22T10:12:50.000Z"
        },
        {
            "id": 2136334,
            "content_html": "",
            "url": "https://finance.sina.cn/7x24/2021-04-22/detail-ikmyaawc1226666.d.html",
            "title": "陶氏化学(DOW.N)：第一季度材料和涂料部门净销售额为21亿美元，同比增长3%。",
            "date_modified": "2021-04-22T10:12:01.000Z"
        },
        {
            "id": 2136329,
            "content_html": "",
            "url": "https://finance.sina.cn/7x24/2021-04-22/detail-ikmyaawc1226616.d.html",
            "title": "陶氏化学(DOW.N)：第一季度包装和特殊塑料部门净销售额为61亿美元，同比增长32%。",
            "date_modified": "2021-04-22T10:11:36.000Z"
        },
        {
            "id": 2136323,
            "content_html": "",
            "url": "https://finance.sina.cn/7x24/2021-04-22/detail-ikmyaawc1226463.d.html",
            "title": "【结汇偏重人民币放量收升创逾一个半月新高】① 人民币兑美元即期周四放量收升创逾一个半月新高，中间价亦时隔逾一个月收复6.5关口，交易员称，美债收益率涨势消退降低美元吸引力，美元指数重新跌向91关口支撑，加上结汇需求旺盛，人民币顺势走升；他们并指出，短期欧元料继续走强，美元走势偏空；一中资行交易员称，近期欧元仍将继续走强，美元或维持偏弱走势；② 知名外媒最新调查显示，美国经济今年的增速将创数十年来最快，傲视其他主要国家，展望大幅上调，但另一波新冠疫情飙升是接下来三个月的最大风险；今年美国经济料将平均成长6.2%，如果成真，将成为自1984年以来最快的年度增长；③ 全球汇市方面，欧元周四小幅上涨，欧洲央行今日晚些时候将召开会议，若对经济前景发表正面评论或有缩减购债的暗示，料将推动欧元飙升；欧元兑美元距离3月3日以来最高位不远，自4月开始以来上涨了3%左右。",
            "date_modified": "2021-04-22T10:10:43.000Z"
        },
        {
            "id": 2136312,
            "content_html": "",
            "title": "【飞科电器年度报告：2020年度净利同比减少6.93% 拟10派10元】财联社4月22日讯，飞科电器公告，公司2020年度实现总营收35.68亿元，同比减少5.09%，归属于上市公司股东的净利润6.38亿元，同比减少6.93%。拟10派10元。",
            "date_modified": "2021-04-22T10:08:58.000Z"
        },
        {
            "id": 2136306,
            "content_html": "",
            "url": "https://finance.sina.cn/7x24/2021-04-22/detail-ikmxzfmk8365925.d.html",
            "title": "万科A：一季度实现净利润12.92亿元，同比增长3.44%。",
            "date_modified": "2021-04-22T10:08:02.000Z"
        },
        {
            "id": 2136299,
            "content_html": "",
            "url": "https://finance.sina.cn/7x24/2021-04-22/detail-ikmyaawc1225718.d.html",
            "title": "市场消息：苹果准备对其移动软件进行重大改进。",
            "date_modified": "2021-04-22T10:06:56.000Z"
        },
        {
            "id": 2136297,
            "content_html": "",
            "url": "https://finance.sina.cn/7x24/2021-04-22/detail-ikmxzfmk8365650.d.html",
            "title": "东风汽车：公司于2021年4月22日收到襄阳市财政局拨付的2016-2018年度新能源汽车推广应用补贴资金3.2亿元。",
            "date_modified": "2021-04-22T10:06:28.000Z"
        },
        {
            "id": 2136292,
            "content_html": "",
            "url": "https://finance.sina.cn/7x24/2021-04-22/detail-ikmyaawc1225598.d.html",
            "title": "【特斯拉已提交行车数据】4月22日下午5时46分，特斯拉相关工作人员告诉记者，22日上午他们已经将加盖公章的数据拿到了郑州市市场监督管理局，但该局工作人员建议，由当事车主来对接接收。该工作人员称，22日下午，他们多次致电张女士及其家属，但一直未能联系上。22日下午5时30分，他们已经通过快递的形式，将相关数据寄出。（凤凰网财经）",
            "date_modified": "2021-04-22T10:06:15.000Z"
        },
        {
            "id": 2136288,
            "content_html": "",
            "url": "https://finance.sina.cn/7x24/2021-04-22/detail-ikmxzfmk8365537.d.html",
            "title": "陶氏化学(DOW.N)：2021年Q1每股盈利1.32美元，市场预期1.09美元，去年同期0.32美元。",
            "date_modified": "2021-04-22T10:05:57.000Z"
        },
        {
            "id": 2136287,
            "content_html": "",
            "url": "https://finance.sina.cn/7x24/2021-04-22/detail-ikmxzfmk8365493.d.html",
            "title": "陶氏化学(DOW.N)：2021年Q1营收118.82亿美元，市场预期110.92亿美元，去年同期97.7亿美元。",
            "date_modified": "2021-04-22T10:05:41.000Z"
        },
        {
            "id": 2136283,
            "content_html": "",
            "url": "https://finance.sina.cn/7x24/2021-04-22/detail-ikmyaawc1225389.d.html",
            "title": "英国4月CBI季度制造业景气指数录得38，为1973年4月以来最高。",
            "date_modified": "2021-04-22T10:05:12.000Z"
        },
        {
            "id": 2136279,
            "content_html": "",
            "url": "https://finance.sina.cn/7x24/2021-04-22/detail-ikmxzfmk8365223.d.html",
            "title": "市场消息：苹果(AAPL.O)正在升级imessage以与Whatsapp竞争。",
            "date_modified": "2021-04-22T10:04:23.000Z"
        },
        {
            "id": 2136277,
            "content_html": "",
            "url": "https://finance.sina.cn/7x24/2021-04-22/detail-ikmyaawc1225157.d.html",
            "title": "【飞科电器年度报告：2020年度净利同比减少6.93% 拟10派10元】飞科电器公告，公司2020年度实现总营收35.68亿元，同比减少5.09%，归属于上市公司股东的净利润6.38亿元，同比减少6.93%。拟10派10元。",
            "date_modified": "2021-04-22T10:04:01.000Z"
        },
        {
            "id": 2136268,
            "content_html": "",
            "url": "https://finance.sina.cn/7x24/2021-04-22/detail-ikmxzfmk8364650.d.html",
            "title": "市场消息：美国总统拜登将在周四的气候峰会上承诺美国将减排50-52%，为美国前总统奥巴马设定的目标的两倍。",
            "date_modified": "2021-04-22T10:01:28.000Z"
        },
        {
            "id": 2136266,
            "content_html": "",
            "url": "https://finance.sina.cn/7x24/2021-04-22/detail-ikmxzfmk8364595.d.html",
            "title": "印度经济统计小组负责人：目标在2022年10月至11月发布服务业指数。 服务部门可能包括多达70个分部门。",
            "date_modified": "2021-04-22T10:01:07.000Z"
        },
        {
            "id": 2136265,
            "content_html": "",
            "title": "英国4月CBI工业订单差值前值 -5；预期 2；公布 -8。",
            "date_modified": "2021-04-22T10:00:32.000Z"
        },
        {
            "id": 2136263,
            "content_html": "",
            "url": "https://finance.sina.cn/7x24/2021-04-22/detail-ikmyaawc1224200.d.html",
            "title": "【亿纬锂能：一季度净利同比增长156.22%】亿纬锂能公告，公司一季度实现营业收入29.58亿元，同比增125.98%；净利润6.47亿元，同比增长156.22%；基本每股收益0.34元。",
            "date_modified": "2021-04-22T09:59:17.000Z"
        },
        {
            "id": 2136258,
            "content_html": "",
            "url": "https://finance.sina.cn/7x24/2021-04-22/detail-ikmxzfmk8363514.d.html",
            "title": "乘联会：当前疫苗接种率不断提升，将促进餐饮、服务业等持续修复。正在举行的上海车展携众多智能、电动化新车型，将近期车市的热度再度推向高潮。宏观经济和政策层面继续对车市的支撑力度，但芯片短缺的影响浮现，预计在二季度逐渐开始对终端销售带来一定影响。",
            "date_modified": "2021-04-22T09:54:01.000Z"
        },
        {
            "id": 2136256,
            "content_html": "",
            "url": "https://finance.sina.cn/7x24/2021-04-22/detail-ikmyaawc1223426.d.html",
            "title": "【三利谱：一季度净利同比增长570%】三利谱公告，公司2021年度一季度实现净利润7653万元，同比增长570%。",
            "date_modified": "2021-04-22T09:53:50.000Z"
        },
        {
            "id": 2136252,
            "content_html": "",
            "url": "https://finance.sina.cn/7x24/2021-04-22/detail-ikmyaawc1223145.d.html",
            "title": "日本内阁官房长官加藤胜信在22日的记者会上表示，在印度发现的“双重变异”新冠病毒已在日本国内发现5例。据悉这种病毒可能有极强的传染性，并很难被免疫。",
            "date_modified": "2021-04-22T09:51:52.000Z"
        },
        {
            "id": 2136251,
            "content_html": "",
            "url": "https://finance.sina.cn/7x24/2021-04-22/detail-ikmyaawc1222853.d.html",
            "title": "匈牙利央行将一周存款利率维持在0.75%不变。",
            "date_modified": "2021-04-22T09:50:36.000Z"
        },
        {
            "id": 2136250,
            "content_html": "",
            "url": "https://finance.sina.cn/7x24/2021-04-22/detail-ikmxzfmk8362661.d.html",
            "title": "花旗：将纳斯达克OMX交易所(NDAQ.O)目标价从164美元上调至167美元。",
            "date_modified": "2021-04-22T09:49:47.000Z"
        },
        {
            "id": 2136249,
            "content_html": "",
            "url": "https://finance.sina.cn/7x24/2021-04-22/detail-ikmxzfmk8362542.d.html",
            "title": "葛洲坝：预计第一季度净利润与上年同期相比将增加增加2.5亿-3亿元，同比增长60%-75%。一季度公司持续推进结构调整和转型升级，工程建设业务盈利增长、高速公路业务恢复正常收费、水泥业务恢复正常经营，各业务板块经营效益提升明显，盈利能力进一步提高。",
            "date_modified": "2021-04-22T09:49:09.000Z"
        },
        {
            "id": 2136248,
            "content_html": "",
            "url": "https://finance.sina.cn/7x24/2021-04-22/detail-ikmyaawc1222295.d.html",
            "title": "市场消息：英国计划在下月推出“疫苗护照”。",
            "date_modified": "2021-04-22T09:47:43.000Z"
        },
        {
            "id": 2136247,
            "content_html": "",
            "url": "https://finance.sina.cn/7x24/2021-04-22/detail-ikmxzfmk8362322.d.html",
            "title": "苏泊尔：拟以3.18亿-6.36亿元回购股份，本次回购股份的最高价不超过人民币77.80元/股。",
            "date_modified": "2021-04-22T09:47:26.000Z"
        },
        {
            "id": 2136246,
            "content_html": "",
            "title": "数据显示，近日，B站关联公司上海幻电信息科技有限公司新增“神弹幕”、“高能弹幕”商标申请信息，国际分类涉及设计研究，目前商标状态均为“注册申请中”。",
            "date_modified": "2021-04-22T09:47:15.000Z"
        },
        {
            "id": 2136245,
            "content_html": "",
            "url": "https://finance.sina.cn/7x24/2021-04-22/detail-ikmyaawc1222120.d.html",
            "title": "费氏全球能源咨询公司（FGE）：印度疫情大爆发，5月份石油需求减少55万桶/日。",
            "date_modified": "2021-04-22T09:46:34.000Z"
        },
        {
            "id": 2136244,
            "content_html": "",
            "url": "https://finance.sina.cn/7x24/2021-04-22/detail-ikmyaawc1221849.d.html",
            "title": "【全球首个时速160公里内嵌式磁浮交通系统正式亮相】2021成都国际工业博览会22日在成都举行。当日，由成都市新筑路桥机械股份有限公司推出的全球首个时速160公里的内嵌式磁浮交通系统正式亮相。内嵌式磁浮交通系统，是成都工业与国际先进技术合作的代表作品。在成都新津建设了3.6公里的中低速磁浮模拟商业运营试验线，列车最高运行时速为169公里，速度满足市域等交通的需要。（36氪）",
            "date_modified": "2021-04-22T09:45:06.000Z"
        },
        {
            "id": 2136243,
            "content_html": "",
            "url": "https://finance.sina.cn/7x24/2021-04-22/detail-ikmxzfmk8361867.d.html",
            "title": "【因股票代币发行 币安受到欧洲监管机构的审查】币安上周推出了其股票代币发行，因此受到欧洲监管机构的监管。英国《金融时报》周四报道了这一消息，称包括英国金融行为监管局（FCA）在内的欧洲监管机构正在研究币安在进行股票代币交易之前是否遵守安全规则。",
            "date_modified": "2021-04-22T09:44:43.000Z"
        },
        {
            "id": 2136242,
            "content_html": "",
            "url": "https://finance.sina.cn/7x24/2021-04-22/detail-ikmyaawc1221688.d.html",
            "title": "匈牙利总理办公室：根据数据，匈牙利只有1%的疫苗接种者感染了新冠。",
            "date_modified": "2021-04-22T09:44:02.000Z"
        },
        {
            "id": 2136241,
            "content_html": "",
            "url": "https://finance.sina.cn/7x24/2021-04-22/detail-ikmyaawc1221656.d.html",
            "title": "【北京：海底捞、云海肴等49家餐饮企业存在环境问题】近日，北京市生态环境局在第二轮市级“点穴式”执法专项行动中，检查了全市各类企业和点位164家，发现49家餐饮企业存在环境问题，包括海底捞(06862.HK)、云海肴等知名餐饮企业。 下一步，北京市生态环境部门将针对影响北京市大气环境质量的突出问题，结合污染源排放特点，分阶段、分步骤开展“一微克”系列专项执法行动，强化全市大气环境执法，依法严厉打击环境违法行为。",
            "date_modified": "2021-04-22T09:43:52.000Z"
        },
        {
            "id": 2136240,
            "content_html": "",
            "url": "https://finance.sina.cn/7x24/2021-04-22/detail-ikmyaawc1221585.d.html",
            "title": "【花旗中国CEO林钰华：对中国市场态度不变，将加大对公业务投入】花旗中国CEO、花旗银行（中国）行长林钰华表示，退出中国的个人业务是集团总部做出的一个“艰难的决定”，但花旗对中国市场的一贯态度并没有改变，将寻找第三方银行来承接在华个人银行业务，实现业务平稳过渡。（21财经）",
            "date_modified": "2021-04-22T09:43:33.000Z"
        },
        {
            "id": 2136239,
            "content_html": "",
            "url": "https://finance.sina.cn/7x24/2021-04-22/detail-ikmyaawc1220756.d.html",
            "title": "【英威腾：一季度净利润同比增长758%】英威腾发布2021年一季报，一季度净利润3711.02万元，同比增长757.55%；营业收入5.79亿元，同比增长79.11%。同日发布2020年年报，归母净利润1.36亿元，上年同期净亏损2.98亿元，扭亏为盈；营业收入22.86亿元，同比增长1.98%；基本每股收益0.18元。",
            "date_modified": "2021-04-22T09:40:12.000Z"
        },
        {
            "id": 2136238,
            "content_html": "",
            "url": "https://finance.sina.cn/7x24/2021-04-22/detail-ikmyaawc1220549.d.html",
            "title": "世界卫生组织表示，与欧洲药品管理局共同对俄罗斯的“卫星-V”新冠疫苗的下一轮评估预计将于5月10日开始。",
            "date_modified": "2021-04-22T09:39:21.000Z"
        },
        {
            "id": 2136237,
            "content_html": "",
            "url": "https://finance.sina.cn/7x24/2021-04-22/detail-ikmyaawc1220494.d.html",
            "title": "利比亚国家石油公司声明：由于预算问题可能进一步下降，利比亚石油产量降至100万桶/日。",
            "date_modified": "2021-04-22T09:39:05.000Z"
        },
        {
            "id": 2136236,
            "content_html": "",
            "url": "https://finance.sina.cn/7x24/2021-04-22/detail-ikmxzfmk8360606.d.html",
            "title": "【奥瑞金：一季度净利润同比增长573%】奥瑞金公告，2021年一季度实现净利润2亿元，同比增长572.51%。",
            "date_modified": "2021-04-22T09:38:18.000Z"
        },
        {
            "id": 2136235,
            "content_html": "",
            "url": "https://finance.sina.cn/7x24/2021-04-22/detail-ikmyaawc1220346.d.html",
            "title": "市场消息：挪威向瑞典和冰岛借出阿斯利康新冠疫苗。",
            "date_modified": "2021-04-22T09:38:07.000Z"
        },
        {
            "id": 2136234,
            "content_html": "",
            "url": "https://finance.sina.cn/7x24/2021-04-22/detail-ikmyaawc1220319.d.html",
            "title": "市场消息：滴滴出行在IPO前募资16亿美元。",
            "date_modified": "2021-04-22T09:37:57.000Z"
        },
        {
            "id": 2136233,
            "content_html": "",
            "url": "https://finance.sina.cn/7x24/2021-04-22/detail-ikmyaawc1220266.d.html",
            "title": "市场消息：捷豹路虎暂停了两家工厂的部分生产。",
            "date_modified": "2021-04-22T09:37:36.000Z"
        },
        {
            "id": 2136232,
            "content_html": "",
            "url": "https://finance.sina.cn/7x24/2021-04-22/detail-ikmyaawc1220137.d.html",
            "title": "ST德威：公司拟与深圳市千懿氢能有限责任公司利用各自业务领域具有的专业优势和项目资源，就德威氢燃料电池项目在深圳开发、投资、建设、运营全方位层面建立战略合作关系。",
            "date_modified": "2021-04-22T09:36:43.000Z"
        },
        {
            "id": 2136231,
            "content_html": "",
            "url": "https://finance.sina.cn/7x24/2021-04-22/detail-ikmyaawc1220114.d.html",
            "title": "【风语筑：一季度净利润同比增长240%】风语筑公告，2021年一季度实现净利润1.58亿元，同比增长239.77%。",
            "date_modified": "2021-04-22T09:36:29.000Z"
        },
        {
            "id": 2136230,
            "content_html": "",
            "url": "https://finance.sina.cn/7x24/2021-04-22/detail-ikmxzfmk8360302.d.html",
            "title": "【印度和欧盟正在商谈全球基建合作计划，或将于5月公布】欧盟和印度正在商谈在世界各地合作进行基础设施建设，该计划预计在5月8日印度与欧盟召开的视频峰会中公布。相关外交人士透露，印度和欧盟将会侧重于各自领土上的合作项目以及在第三国的计划，并在金融和法治等领域制定标准，但诸如投资基金的来源等具体条款还未被敲定。预计资金来源将包括政府和私人资金。",
            "date_modified": "2021-04-22T09:36:15.000Z"
        },
        {
            "id": 2136229,
            "content_html": "",
            "url": "https://finance.sina.cn/7x24/2021-04-22/detail-ikmyaawc1219997.d.html",
            "title": "汇丰银行：我们有到2030年实现净零排放的雄心。",
            "date_modified": "2021-04-22T09:35:49.000Z"
        },
        {
            "id": 2136228,
            "content_html": "",
            "title": "克里姆林宫：总统普京已收到乌克兰总统提出的会晤请求，表示“如果他认为有必要，将做出回应”。",
            "date_modified": "2021-04-22T09:35:39.000Z"
        },
        {
            "id": 2136227,
            "content_html": "",
            "url": "https://finance.sina.cn/7x24/2021-04-22/detail-ikmxzfmk8360186.d.html",
            "title": "【海峡股份：一季度净利润同比增长56%】海峡股份公告，2021年一季度实现净利润1.15亿元，同比增长55.56%。",
            "date_modified": "2021-04-22T09:35:31.000Z"
        },
        {
            "id": 2136226,
            "content_html": "",
            "url": "https://finance.sina.cn/7x24/2021-04-22/detail-ikmxzfmk8360116.d.html",
            "title": "印度制药公司DR. REDDY’S 称，预计5月底之前进口俄罗斯的SPUTNIK V新冠疫苗。",
            "date_modified": "2021-04-22T09:35:08.000Z"
        },
        {
            "id": 2136225,
            "content_html": "",
            "title": "春风动力：持股5.99%的股东老板集团拟减持不超过1.12%。",
            "date_modified": "2021-04-22T09:34:45.000Z"
        },
        {
            "id": 2136224,
            "content_html": "",
            "url": "https://finance.sina.cn/7x24/2021-04-22/detail-ikmxzfmk8359992.d.html",
            "title": "思摩尔国际在港交所公告，第一季度营收11.79亿元，同比增长403%。",
            "date_modified": "2021-04-22T09:34:29.000Z"
        },
        {
            "id": 2136223,
            "content_html": "",
            "url": "https://finance.sina.cn/7x24/2021-04-22/detail-ikmyaawc1219697.d.html",
            "title": "【三花智控：一季度净利同比增长70.36%】三花智控公告，公司2021年度一季度实现净利润3.6亿元，同比增长70.36%。",
            "date_modified": "2021-04-22T09:34:16.000Z"
        },
        {
            "id": 2136222,
            "content_html": "",
            "url": "https://finance.sina.cn/7x24/2021-04-22/detail-ikmyaawc1219663.d.html",
            "title": "芝加哥大豆期货涨至每蒲式耳15美元，为2014年以来最高。",
            "date_modified": "2021-04-22T09:34:08.000Z"
        },
        {
            "id": 2136221,
            "content_html": "",
            "url": "https://finance.sina.cn/7x24/2021-04-22/detail-ikmyaawc1219627.d.html",
            "title": "【*ST辅仁下修业绩预告：预计2020年净亏损12.92亿元左右】*ST辅仁下修2020年业绩预告，经财务部门再次测算，预计2020年年度净利润将亏损12.92亿元左右，此前预计净利润将亏损7.8亿元到9.6亿元。",
            "date_modified": "2021-04-22T09:33:50.000Z"
        },
        {
            "id": 2136220,
            "content_html": "",
            "url": "https://finance.sina.cn/7x24/2021-04-22/detail-ikmxzfmk8359690.d.html",
            "title": "春风动力：持股5.99%的股东老板集团拟减持不超过1.12%。",
            "date_modified": "2021-04-22T09:32:38.000Z"
        },
        {
            "id": 2136219,
            "content_html": "",
            "url": "https://finance.sina.cn/7x24/2021-04-22/detail-ikmxzfmk8359579.d.html",
            "title": "【南向资金今日净流入58.93亿港元】南向资金今日净流入58.93亿港元。港股通(沪)方面，中国移动、长城汽车净买入居前，分别获净买入6.21亿港元、4.85亿港元。港股通(深)方面，安踏体育、中国移动净买入居前，分别获净买入6.00亿港元、4.41亿港元。",
            "date_modified": "2021-04-22T09:31:50.000Z"
        },
        {
            "id": 2136218,
            "content_html": "",
            "url": "https://finance.sina.cn/7x24/2021-04-22/detail-ikmyaawc1219167.d.html",
            "title": "  【北向资金净流出15.97亿 中国平安净卖出9.29亿】北向资金今日净流出15.97亿。中国平安净卖出9.29亿，立讯精密净卖出5.49亿，恒瑞医药净卖出3.36亿，贵州茅台净卖出3.20亿。",
            "date_modified": "2021-04-22T09:30:58.000Z"
        },
        {
            "id": 2136217,
            "content_html": "",
            "url": "https://finance.sina.cn/7x24/2021-04-22/detail-ikmxzfmk8359043.d.html",
            "title": "安德利：终止非公开发行A股股票事项并撤回申请文件。",
            "date_modified": "2021-04-22T09:29:55.000Z"
        },
        {
            "id": 2136216,
            "content_html": "",
            "url": "https://finance.sina.cn/7x24/2021-04-22/detail-ikmxzfmk8358947.d.html",
            "title": "【中钢协：后期钢价难以持续大幅上涨】今年一季度以来钢价屡创新高。中国钢铁工业协会近日发布报告称，由于前期涨幅较大、涨速较快，向下游行业传导困难加大，后期钢价难以持续大幅上涨，应以小幅波动为主。",
            "date_modified": "2021-04-22T09:29:14.000Z"
        },
        {
            "id": 2136215,
            "content_html": "",
            "url": "https://finance.sina.cn/7x24/2021-04-22/detail-ikmxzfmk8358762.d.html",
            "title": "沪电股份：一季度实现净利润2.2亿元，同比增长3.20%。",
            "date_modified": "2021-04-22T09:28:02.000Z"
        },
        {
            "id": 2136214,
            "content_html": "",
            "url": "https://finance.sina.cn/7x24/2021-04-22/detail-ikmyaawc1218343.d.html",
            "title": "韦尔股份：一季度实现净利润10.4亿元，同比增长133.84%。",
            "date_modified": "2021-04-22T09:26:59.000Z"
        },
        {
            "id": 2136213,
            "content_html": "",
            "url": "https://finance.sina.cn/7x24/2021-04-22/detail-ikmxzfmk8358360.d.html",
            "title": "今日有媒体就陶琳是否已“引咎辞职”向特斯拉进行求证，特斯拉客服工作人员回应称“此事已超出其职务回应范围”，并表示：“相关信息请以特斯拉官方（微博）渠道为准”。",
            "date_modified": "2021-04-22T09:25:41.000Z"
        },
        {
            "id": 2136211,
            "content_html": "",
            "url": "https://finance.sina.cn/7x24/2021-04-22/detail-ikmyaawc1217958.d.html",
            "title": "  富临运业：持股7.36%的股东王成盛拟减持不超过3%。",
            "date_modified": "2021-04-22T09:24:51.000Z"
        },
        {
            "id": 2136209,
            "content_html": "",
            "url": "https://finance.sina.cn/7x24/2021-04-22/detail-ikmyaawc1217919.d.html",
            "title": "仙鹤股份公告，公司2021年度一季度实现净利润2.8亿元，同比增长167.49%。主要系产能释放，销量增加所致。",
            "date_modified": "2021-04-22T09:24:38.000Z"
        },
        {
            "id": 2136208,
            "content_html": "",
            "url": "https://finance.sina.cn/7x24/2021-04-22/detail-ikmxzfmk8358065.d.html",
            "title": "【摩根大通正在招聘以太坊和区块链开发人员】摩根大通正在积极招聘以太坊和区块链开发人员。该职位发布在美国招聘网站Glassdoor上，要求应聘者具备编写智能合约、部署业务应用程序和验证区块链加密协议经验。",
            "date_modified": "2021-04-22T09:24:02.000Z"
        },
        {
            "id": 2136207,
            "content_html": "",
            "title": "【苹果CEO库克：M1芯片版Mac电脑销量已超过英特尔版】在苹果2021春季发布会上，苹果首席执行官蒂姆·库克表示，搭载苹果自研芯片M1的Mac电脑销量已经超过了搭载英特尔处理器的Mac电脑。库克还表示，尽管去年11月才发布，但搭载M1芯片的Mac电脑销量现在占据了其Mac销量的大部分。",
            "date_modified": "2021-04-22T09:23:47.000Z"
        },
        {
            "id": 2136206,
            "content_html": "",
            "url": "https://finance.sina.cn/7x24/2021-04-22/detail-ikmyaawc1217686.d.html",
            "title": "【中国棉花协会推动行业自主标准体系建设，打造中国棉花品质国货】22日中国棉花协会发布《“中国棉花”生产管理规范》，推动行业自主标准体系建设。《规范》从生产标准出发，通过建立规范化、标准化、负责任、可持续的棉花生产、管理模式，帮助种植者不断改进生产方式，在保障优质棉花供应的同时减少对生态环境的负面影响，保护和持续利用自然资源，保障劳动者权益与福祉。（新华社）",
            "date_modified": "2021-04-22T09:23:17.000Z"
        },
        {
            "id": 2136205,
            "content_html": "",
            "url": "https://finance.sina.cn/7x24/2021-04-22/detail-ikmyaawc1216953.d.html",
            "title": "迎驾贡酒三个交易日累涨22.62%，沪股通累计买入3.49亿元并卖出2.23亿元，三机构合计卖出2.56亿元。",
            "date_modified": "2021-04-22T09:20:18.000Z"
        },
        {
            "id": 2136204,
            "content_html": "",
            "url": "https://finance.sina.cn/7x24/2021-04-22/detail-ikmyaawc1216855.d.html",
            "title": "市场消息：随着核协议谈判的重启，伊朗石油出口可能不会回到2020年的低点。",
            "date_modified": "2021-04-22T09:20:07.000Z"
        },
        {
            "id": 2136203,
            "content_html": "",
            "url": "https://finance.sina.cn/7x24/2021-04-22/detail-ikmyaawc1216769.d.html",
            "title": "市场消息：伊朗的石油出口仍在增加，到目前为止总计约50万桶/日。",
            "date_modified": "2021-04-22T09:19:36.000Z"
        },
        {
            "id": 2136202,
            "content_html": "",
            "url": "https://finance.sina.cn/7x24/2021-04-22/detail-ikmxzfmk8356864.d.html",
            "title": "【快手服务号用户规模达1055万，用户总粉丝数达11亿】在快手光合创作者大会上，快手服务号运营负责人邹振寰首次对外公开服务号运营相关数据，并强调快手服务号会员将永久免费。目前快手服务号用户规模已达1055万，服务号用户总粉丝数达11亿，服务号用户人均可从快手平台获得49条商机。",
            "date_modified": "2021-04-22T09:18:58.000Z"
        },
        {
            "id": 2136201,
            "content_html": "",
            "url": "https://finance.sina.cn/7x24/2021-04-22/detail-ikmxzfmk8356663.d.html",
            "title": "【复星医药：子公司斯鲁利单抗注射液注册申请获受理】复星医药公告，公司控股子公司上海复宏汉霖及其控股子公司自主研发的斯鲁利单抗注射液（即重组抗PD-1人源化单克隆抗体注射液）用于经标准治疗失败的、不可切除或转移性高度微卫星不稳定型实体瘤治疗获国家药品监督管理局药品注册申请受理，并被纳入拟优先审评品种公示名单。",
            "date_modified": "2021-04-22T09:17:44.000Z"
        },
        {
            "id": 2136200,
            "content_html": "",
            "url": "https://finance.sina.cn/7x24/2021-04-22/detail-ikmyaawc1216274.d.html",
            "title": "上海医药：全资子公司上海信谊天平药业有限公司收到国家药品监督管理局颁发的关于硝苯地平缓释片（Ⅱ）的《药品补充申请批准通知书》，该药品通过仿制药质量和疗效一致性评价。",
            "date_modified": "2021-04-22T09:16:44.000Z"
        },
        {
            "id": 2136199,
            "content_html": "",
            "url": "https://finance.sina.cn/7x24/2021-04-22/detail-ikmyaawc1216107.d.html",
            "title": "印度卢比汇率周四在印度央行可能已入市救市的背景下自此前创得的10个月低位反弹。本周稍早，在印度疫情猝不及防恶化的背景下，此前一度长期持稳的卢比汇率录得大幅挫跌。",
            "date_modified": "2021-04-22T09:16:05.000Z"
        },
        {
            "id": 2136198,
            "content_html": "",
            "url": "https://finance.sina.cn/7x24/2021-04-22/detail-ikmyaawc1215975.d.html",
            "title": "【北京将进一步加强房地产市场秩序整治范围覆盖新房二手房及租赁市场】北京市在前期专项执法的基础上，即日起将进一步加强房地产市场秩序整治工作。本轮专项整治范围覆盖新房、二手房及租赁三级市场，将结合“每月一题”工作要求，综合采取集中约谈、巡检暗访、“双随机”抽查、专项检查、联合执法、重点复查等方式，由即日起至年底结束。",
            "date_modified": "2021-04-22T09:15:21.000Z"
        },
        {
            "id": 2136197,
            "content_html": "",
            "url": "https://finance.sina.cn/7x24/2021-04-22/detail-ikmyaawc1215551.d.html",
            "title": "马来西亚新增2875例新冠肺炎确诊病例。",
            "date_modified": "2021-04-22T09:12:58.000Z"
        },
        {
            "id": 2136196,
            "content_html": "",
            "url": "https://finance.sina.cn/7x24/2021-04-22/detail-ikmxzfmk8355742.d.html",
            "title": "日本首相菅义伟：将努力实现减排50%。",
            "date_modified": "2021-04-22T09:12:47.000Z"
        },
        {
            "id": 2136195,
            "content_html": "",
            "url": "https://finance.sina.cn/7x24/2021-04-22/detail-ikmyaawc1215420.d.html",
            "title": "泰国政府发言人：俄罗斯同意向泰国提供“卫星-V”新冠疫苗。",
            "date_modified": "2021-04-22T09:12:16.000Z"
        },
        {
            "id": 2136194,
            "content_html": "",
            "url": "https://finance.sina.cn/7x24/2021-04-22/detail-ikmyaawc1215376.d.html",
            "title": "市场消息：迪拜将2021年7月原油官方售价设定为较阿曼原油价格贴水以0.3美元。",
            "date_modified": "2021-04-22T09:12:00.000Z"
        },
        {
            "id": 2136193,
            "content_html": "",
            "url": "https://finance.sina.cn/7x24/2021-04-22/detail-ikmxzfmk8355521.d.html",
            "title": "卓胜微：一季度实现净利润4.92亿元，同比增长224.34%。主要原因系5G通信技术的发展带动了射频前端市场需求的快速增长。",
            "date_modified": "2021-04-22T09:11:34.000Z"
        },
        {
            "id": 2136191,
            "content_html": "",
            "url": "https://finance.sina.cn/7x24/2021-04-22/detail-ikmyaawc1215224.d.html",
            "title": "【华电国际：拟收购蒙东能源45%股权和福源热电37%股权】华电国际公告，拟向建信投资和中银投资发行普通股A股和可转换公司债券购买其分别持有的蒙东能源45.15%股权和福源热电36.86%股权，标的资产的交易价格暂定为15亿元。",
            "date_modified": "2021-04-22T09:11:19.000Z"
        },
        {
            "id": 2136190,
            "content_html": "",
            "url": "https://finance.sina.cn/7x24/2021-04-22/detail-ikmyaawc1214926.d.html",
            "title": "国恩股份公告，一季度实现净利润1.1亿元，同比增长8.32%。",
            "date_modified": "2021-04-22T09:10:32.000Z"
        },
        {
            "id": 2136189,
            "content_html": "",
            "url": "https://finance.sina.cn/7x24/2021-04-22/detail-ikmxzfmk8355065.d.html",
            "title": "【中煤能源：一季度净利润同比增长441%】中煤能源发布一季度报告，一季度归属于母公司所有者的净利润35亿元，同比增长441.14%；营业收入444亿元，同比增长61.49%；基本每股收益0.26元。",
            "date_modified": "2021-04-22T09:10:24.000Z"
        },
        {
            "id": 2136188,
            "content_html": "",
            "url": "https://finance.sina.cn/7x24/2021-04-22/detail-ikmxzfmk8354879.d.html",
            "title": "北京市住建委：整治重点包括信贷资金违规购房。检查经纪机构是否向购房人推介或怂恿违规使用经营贷、信用贷等金融产品购房；在提供新房、二手房买卖经纪服务时，是否要求购房人书面承诺购房资金不存在挪用银行信贷资金等问题。",
            "date_modified": "2021-04-22T09:09:43.000Z"
        },
        {
            "id": 2136187,
            "content_html": "",
            "url": "https://finance.sina.cn/7x24/2021-04-22/detail-ikmxzfmk8354791.d.html",
            "title": "俄新社：俄罗斯在克里米亚开始军事演习，将有超过1万名士兵参加。",
            "date_modified": "2021-04-22T09:09:14.000Z"
        },
        {
            "id": 2136186,
            "content_html": "",
            "url": "https://finance.sina.cn/7x24/2021-04-22/detail-ikmyaawc1214479.d.html",
            "title": "北京市住建委：依法严厉打击房屋销售、租赁市场违法违规行为，重点针对近期群众反映强烈的机构炒作学区房、经营贷违规进入楼市、群租房治理等问题，依法从严惩处，形成高压态势，规范市场秩序。",
            "date_modified": "2021-04-22T09:08:51.000Z"
        },
        {
            "id": 2136185,
            "content_html": "",
            "url": "https://finance.sina.cn/7x24/2021-04-22/detail-ikmxzfmk8354606.d.html",
            "title": "北京市住房和城乡建设委员会发布关于进一步加强房地产市场秩序整治工作的通知。（北京住建委）",
            "date_modified": "2021-04-22T09:08:21.000Z"
        },
        {
            "id": 2136184,
            "content_html": "",
            "url": "https://finance.sina.cn/7x24/2021-04-22/detail-ikmyaawc1214340.d.html",
            "title": "赞宇科技公告，一季度实现净利润1.82亿元，同比增长75.06%。",
            "date_modified": "2021-04-22T09:08:11.000Z"
        },
        {
            "id": 2136183,
            "content_html": "",
            "title": "【欧盟警告伦敦金融业 不要指望很快获得市场准入】欧盟负责金融服务的委员表示，欧盟并没有任何压力来帮助伦敦金融公司进入欧盟市场，并警告称不会很快做出任何决定，尽管英国为该行业制定不同规则。欧盟可能在今年年中举行一次关于市场准入问题的会议，但欧盟仍在就上个月达成的英国脱欧后监管合作谅解备忘录做后续工作。",
            "date_modified": "2021-04-22T09:07:52.000Z"
        },
        {
            "id": 2136182,
            "content_html": "",
            "url": "https://finance.sina.cn/7x24/2021-04-22/detail-ikmxzfmk8354429.d.html",
            "title": "日本首相菅义伟：日本将向其他国家减排提供支持。",
            "date_modified": "2021-04-22T09:07:32.000Z"
        },
        {
            "id": 2136181,
            "content_html": "",
            "url": "https://finance.sina.cn/7x24/2021-04-22/detail-ikmyaawc1214139.d.html",
            "title": "市场消息：南非将于5月17日开始全面推广强生疫苗。",
            "date_modified": "2021-04-22T09:07:20.000Z"
        },
        {
            "id": 2136180,
            "content_html": "",
            "url": "https://finance.sina.cn/7x24/2021-04-22/detail-ikmyaawc1214002.d.html",
            "title": "祖名股份：公司已对部分产品进行调价，但调价效果存在一定的滞后性。",
            "date_modified": "2021-04-22T09:06:46.000Z"
        },
        {
            "id": 2136179,
            "content_html": "",
            "url": "https://finance.sina.cn/7x24/2021-04-22/detail-ikmyaawc1213956.d.html",
            "title": "【盛和资源：一季度净利3.11亿元 同比增长2787.37%】盛和资源公告，公司2021年度一季度实现净利润3.11亿元，同比增长2787.37%。同时，公司发布年度报告，公司2020年度实现净利润3.23亿元，同比增长218.44%。拟10派0.5元。",
            "date_modified": "2021-04-22T09:06:33.000Z"
        },
        {
            "id": 2136178,
            "content_html": "",
            "url": "https://finance.sina.cn/7x24/2021-04-22/detail-ikmxzfmk8354084.d.html",
            "title": "赞宇科技公告，子公司拟投资建设“年产50万吨日化产品项目”，项目总投资6亿元。",
            "date_modified": "2021-04-22T09:05:48.000Z"
        },
        {
            "id": 2136177,
            "content_html": "",
            "url": "https://finance.sina.cn/7x24/2021-04-22/detail-ikmyaawc1213654.d.html",
            "title": "日本首相菅义伟：将指示各部长们加快应对气候变化的研究。",
            "date_modified": "2021-04-22T09:05:15.000Z"
        },
        {
            "id": 2136176,
            "content_html": "",
            "url": "https://finance.sina.cn/7x24/2021-04-22/detail-ikmxzfmk8353893.d.html",
            "title": "【极米科技：一季度净利润同比增长107%】极米科技发布一季度报告，一季度归母净利润8946.17万元，同比增长106.87%；营业收入8.15亿元，同比增长62.32%；基本每股收益2.15元。",
            "date_modified": "2021-04-22T09:04:59.000Z"
        },
        {
            "id": 2136175,
            "content_html": "",
            "url": "https://finance.sina.cn/7x24/2021-04-22/detail-ikmyaawc1213172.d.html",
            "title": "日本首相菅义伟：创造经济和环境的良性循环对强劲的增长非常重要。",
            "date_modified": "2021-04-22T09:03:07.000Z"
        },
        {
            "id": 2136174,
            "content_html": "",
            "url": "https://finance.sina.cn/7x24/2021-04-22/detail-ikmyaawc1213138.d.html",
            "title": "上海能源公布2021年第一季度报告，实现营业收入20.07亿元，同比增长14.77%；归属于上市公司股东的净利润1.92亿元，同比下降15.86%。",
            "date_modified": "2021-04-22T09:02:54.000Z"
        },
        {
            "id": 2136173,
            "content_html": "",
            "url": "https://finance.sina.cn/7x24/2021-04-22/detail-ikmyaawc1213033.d.html",
            "title": "爱尔眼科：2020年全年净利润为17.24亿元，同比增长25.01%，拟10转3派1.5元。今年一季度实现净利润4.84亿元，同比增长509.88%。",
            "date_modified": "2021-04-22T09:02:22.000Z"
        },
        {
            "id": 2136172,
            "content_html": "",
            "url": "https://finance.sina.cn/7x24/2021-04-22/detail-ikmyaawc1212940.d.html",
            "title": "上交所：5月1日（星期六）至5月5日（星期三）休市，5月6日（星期四）起照常开市。另外，4月25日（星期日）、5月8日（星期六）为周末休市。",
            "date_modified": "2021-04-22T09:01:56.000Z"
        },
        {
            "id": 2136171,
            "content_html": "",
            "url": "https://finance.sina.cn/7x24/2021-04-22/detail-ikmyaawc1212902.d.html",
            "title": "深交所：4月29日（星期四）至5月5日（星期三）不提供港股通服务，5月6日（星期四）起照常开通港股通服务。另外，4月25日（星期日）、5月8日（星期六）为周末休市。",
            "date_modified": "2021-04-22T09:01:45.000Z"
        },
        {
            "id": 2136170,
            "content_html": "",
            "url": "https://finance.sina.cn/7x24/2021-04-22/detail-ikmxzfmk8353141.d.html",
            "title": "市场消息：2020年欧元区的政府债务占GDP的98%。",
            "date_modified": "2021-04-22T09:01:32.000Z"
        }
    ]
}